[
    {
        "company":"JD Sports",
        "ticker":"JD",
        "title":"JD Sports Fashion (OTCMKTS:JDSPY) Shares Up 2.9%",
        "description":"JD Sports Fashion Plc (OTCMKTS:JDSPY \u2013 Get Free Report)\u2019s share price was up 2.9% on Monday . The company traded as high as $1.78 and last traded at $1.75. Approximately 30,996 shares were traded during trading, a decline of 82% from the average daily volume \u2026",
        "content":"JD Sports Fashion Plc (OTCMKTS:JDSPY \u2013 Get Free Report)\u2019s share price was up 2.9% on Monday . The company traded as high as $1.78 and last traded at $1.75. Approximately 30,996 shares were traded dur\u2026 [+978 chars]",
        "url":"https:\/\/www.etfdailynews.com\/2024\/09\/10\/jd-sports-fashion-otcmktsjdspy-shares-up-2-9\/",
        "source":"ETF Daily News",
        "published_at":1725949490000,
        "collected_at":1727696523630,
        "sentiment_label":"Neutral",
        "sentiment_probabolity":0.9933487773,
        "sentiment_vector":0.0
    },
    {
        "company":"JD Sports",
        "ticker":"JD",
        "title":"Shore Capital Reiterates Buy Rating for JD Sports Fashion (LON:JD)",
        "description":"JD Sports Fashion (LON:JD \u2013 Get Free Report)\u2018s stock had its \u201cbuy\u201d rating reissued by Shore Capital in a research note issued to investors on Monday, MarketBeat.com reports. A number of other equities analysts have also recently issued reports on JD. Deutsche\u2026",
        "content":"JD Sports Fashion (LON:JD \u2013 Get Free Report)\u2018s stock had its \u201cbuy\u201d rating reissued by Shore Capital in a research note issued to investors on Monday, MarketBeat.com reports.\r\nA number of other equiti\u2026 [+2338 chars]",
        "url":"https:\/\/www.etfdailynews.com\/2024\/09\/18\/shore-capital-reiterates-buy-rating-for-jd-sports-fashion-lonjd\/",
        "source":"ETF Daily News",
        "published_at":1726639733000,
        "collected_at":1727696523630,
        "sentiment_label":"Positive",
        "sentiment_probabolity":0.9999853373,
        "sentiment_vector":0.9999853373
    },
    {
        "company":"JD Sports",
        "ticker":"JD",
        "title":"JD Sports Fashion Plc (OTCMKTS:JDDSF) Short Interest Update",
        "description":"JD Sports Fashion Plc (OTCMKTS:JDDSF \u2013 Get Free Report) saw a large growth in short interest during the month of August. As of August 15th, there was short interest totalling 9,682,200 shares, a growth of 8.8% from the July 31st total of 8,902,800 shares. Bas\u2026",
        "content":"JD Sports Fashion Plc (OTCMKTS:JDDSF \u2013 Get Free Report) saw a large growth in short interest during the month of August. As of August 15th, there was short interest totalling 9,682,200 shares, a grow\u2026 [+1383 chars]",
        "url":"https:\/\/www.etfdailynews.com\/2024\/09\/03\/jd-sports-fashion-plc-otcmktsjddsf-short-interest-update\/",
        "source":"ETF Daily News",
        "published_at":1725345291000,
        "collected_at":1727696523630,
        "sentiment_label":"Neutral",
        "sentiment_probabolity":0.9821484089,
        "sentiment_vector":0.0
    },
    {
        "company":"JD Sports",
        "ticker":"JD",
        "title":"JD Sports Fashion (OTCMKTS:JDDSF) versus Guess? (NYSE:GES) Financial Survey",
        "description":"Guess? (NYSE:GES \u2013 Get Free Report) and JD Sports Fashion (OTCMKTS:JDDSF \u2013 Get Free Report) are both consumer discretionary companies, but which is the better stock? We will contrast the two companies based on the strength of their institutional ownership, ri\u2026",
        "content":"Guess? (NYSE:GES \u2013 Get Free Report) and JD Sports Fashion (OTCMKTS:JDDSF \u2013 Get Free Report) are both consumer discretionary companies, but which is the better stock? We will contrast the two companie\u2026 [+5247 chars]",
        "url":"https:\/\/www.etfdailynews.com\/2024\/09\/14\/jd-sports-fashion-otcmktsjddsf-versus-guess-nyseges-financial-survey\/",
        "source":"ETF Daily News",
        "published_at":1726290908000,
        "collected_at":1727696523630,
        "sentiment_label":"Positive",
        "sentiment_probabolity":0.8444791436,
        "sentiment_vector":0.8444791436
    },
    {
        "company":"JD Sports",
        "ticker":"JD",
        "title":"Comparing Shoe Carnival (NASDAQ:SCVL) & JD Sports Fashion (OTCMKTS:JDDSF)",
        "description":"Shoe Carnival (NASDAQ:SCVL \u2013 Get Free Report) and JD Sports Fashion (OTCMKTS:JDDSF \u2013 Get Free Report) are both retail\/wholesale companies, but which is the better stock? We will contrast the two companies based on the strength of their dividends, institutiona\u2026",
        "content":"Shoe Carnival (NASDAQ:SCVL \u2013 Get Free Report) and JD Sports Fashion (OTCMKTS:JDDSF \u2013 Get Free Report) are both retail\/wholesale companies, but which is the better stock? We will contrast the two comp\u2026 [+4636 chars]",
        "url":"https:\/\/www.etfdailynews.com\/2024\/09\/19\/comparing-shoe-carnival-nasdaqscvl-jd-sports-fashion-otcmktsjddsf\/",
        "source":"ETF Daily News",
        "published_at":1726791935000,
        "collected_at":1727696523630,
        "sentiment_label":"Neutral",
        "sentiment_probabolity":0.9055010676,
        "sentiment_vector":0.0
    },
    {
        "company":"JD Sports",
        "ticker":"JD",
        "title":"JD Sports Fashion (LON:JD) Share Price Crosses Above Two Hundred Day Moving Average of $121.28",
        "description":"Shares of JD Sports Fashion Plc (LON:JD \u2013 Get Free Report) crossed above its 200-day moving average during trading on Friday . The stock has a 200-day moving average of GBX 121.28 ($1.60) and traded as high as GBX 140.23 ($1.85). JD Sports Fashion shares last\u2026",
        "content":"Shares of JD Sports Fashion Plc (LON:JD \u2013 Get Free Report) crossed above its 200-day moving average during trading on Friday . The stock has a 200-day moving average of GBX 121.28 ($1.60) and traded \u2026 [+2471 chars]",
        "url":"https:\/\/www.etfdailynews.com\/2024\/08\/31\/jd-sports-fashion-lonjd-share-price-crosses-above-two-hundred-day-moving-average-of-121-28\/",
        "source":"ETF Daily News",
        "published_at":1725086229000,
        "collected_at":1727696523630,
        "sentiment_label":"Neutral",
        "sentiment_probabolity":0.9999991655,
        "sentiment_vector":0.0
    },
    {
        "company":"JD Sports",
        "ticker":"JD",
        "title":"JD Sports Fashion (LON:JD) Stock Price Crosses Above Two Hundred Day Moving Average of $124.71",
        "description":"JD Sports Fashion Plc (LON:JD - Get Free Report) crossed above its 200-day moving average during trading on Monday . The stock has a 200-day moving average of GBX 124.71 ($1.66) and traded as high as GBX 157.90 ($2.11). JD Sports Fashion shares last traded at\u2026",
        "content":"JD Sports Fashion Plc (LON:JD - Get Free Report) crossed above its 200-day moving average during trading on Monday . The stock has a 200-day moving average of GBX 124.71 ($1.66) and traded as high as\u2026 [+138 chars]",
        "url":"https:\/\/biztoc.com\/x\/58789b10c7942cd1",
        "source":"Biztoc.com",
        "published_at":1727160512000,
        "collected_at":1727696523630,
        "sentiment_label":"Neutral",
        "sentiment_probabolity":0.9999997616,
        "sentiment_vector":0.0
    },
    {
        "company":"JD Sports",
        "ticker":"JD",
        "title":"JD Sports Fashion (LON:JD) Stock Price Crosses Above Two Hundred Day Moving Average of $124.71",
        "description":"JD Sports Fashion Plc (LON:JD \u2013 Get Free Report) crossed above its 200-day moving average during trading on Monday . The stock has a 200-day moving average of GBX 124.71 ($1.66) and traded as high as GBX 157.90 ($2.11). JD Sports Fashion shares last traded at\u2026",
        "content":"JD Sports Fashion Plc (LON:JD \u2013 Get Free Report) crossed above its 200-day moving average during trading on Monday . The stock has a 200-day moving average of GBX 124.71 ($1.66) and traded as high as\u2026 [+2413 chars]",
        "url":"https:\/\/www.etfdailynews.com\/2024\/09\/24\/jd-sports-fashion-lonjd-stock-price-crosses-above-two-hundred-day-moving-average-of-124-71\/",
        "source":"ETF Daily News",
        "published_at":1727159993000,
        "collected_at":1727696523630,
        "sentiment_label":"Neutral",
        "sentiment_probabolity":0.9999997616,
        "sentiment_vector":0.0
    },
    {
        "company":"JD Sports",
        "ticker":"JD",
        "title":"JD Sports Fashion Plc (LON:JD) Given Average Rating of \u201cModerate Buy\u201d by Brokerages",
        "description":"Shares of JD Sports Fashion Plc (LON:JD \u2013 Get Free Report) have been assigned a consensus rating of \u201cModerate Buy\u201d from the six research firms that are covering the stock, Marketbeat reports. One investment analyst has rated the stock with a sell recommendati\u2026",
        "content":"Shares of JD Sports Fashion Plc (LON:JD \u2013 Get Free Report) have been assigned a consensus rating of \u201cModerate Buy\u201d from the six research firms that are covering the stock, Marketbeat reports. One inv\u2026 [+2421 chars]",
        "url":"https:\/\/www.etfdailynews.com\/2024\/09\/06\/jd-sports-fashion-plc-lonjd-given-average-rating-of-moderate-buy-by-brokerages\/",
        "source":"ETF Daily News",
        "published_at":1725614811000,
        "collected_at":1727696523630,
        "sentiment_label":"Positive",
        "sentiment_probabolity":0.8988823891,
        "sentiment_vector":0.8988823891
    },
    {
        "company":"JD Sports",
        "ticker":"JD",
        "title":"Short Interest in JD Sports Fashion Plc (OTCMKTS:JDSPY) Expands By 51.2%",
        "description":"JD Sports Fashion Plc (OTCMKTS:JDSPY \u2013 Get Free Report) was the recipient of a significant increase in short interest during the month of September. As of September 15th, there was short interest totalling 31,300 shares, an increase of 51.2% from the August 3\u2026",
        "content":"JD Sports Fashion Plc (OTCMKTS:JDSPY \u2013 Get Free Report) was the recipient of a significant increase in short interest during the month of September. As of September 15th, there was short interest tot\u2026 [+1360 chars]",
        "url":"https:\/\/www.etfdailynews.com\/2024\/09\/27\/short-interest-in-jd-sports-fashion-plc-otcmktsjdspy-expands-by-51-2\/",
        "source":"ETF Daily News",
        "published_at":1727456237000,
        "collected_at":1727696523630,
        "sentiment_label":"Positive",
        "sentiment_probabolity":0.9982863069,
        "sentiment_vector":0.9982863069
    },
    {
        "company":"JD Sports",
        "ticker":"JD",
        "title":"Mrs S Hodgeon v JD Sports Fashion plc: 2407976\/2023",
        "description":"Employment Tribunal decision.",
        "content":"We use some essential cookies to make this website work.\r\nWed like to set additional cookies to understand how you use GOV.UK, remember your settings and improve government services.\r\nWe also use coo\u2026 [+70 chars]",
        "url":"https:\/\/www.gov.uk\/employment-tribunal-decisions\/mrs-s-hodgeon-v-jd-sports-fashion-plc-2407976-slash-2023",
        "source":"Www.gov.uk",
        "published_at":1726065916000,
        "collected_at":1727696523630,
        "sentiment_label":"Neutral",
        "sentiment_probabolity":0.9993143082,
        "sentiment_vector":0.0
    },
    {
        "company":"JD Sports",
        "ticker":"JD",
        "title":"La croissance devrait rester forte pour le distributeur d\u2019articles de sports JD Sports",
        "description":"En bourse, le titre a atteint des sommets boursiers vers la fin 2021, mais il se cherche depuis un second souffle. ...",
        "content":"\"Une trajectoire favorable\"\r\nLe groupe doit sa croissance aux contrats de distribution exclusifs sign\u00e9s avec des groupes comme Nike ou Adidas, qui donnent la primaut\u00e9 de certaines collections tr\u00e8s re\u2026 [+1282 chars]",
        "url":"https:\/\/www.lalibre.be\/economie\/entreprises-startup\/2024\/09\/27\/la-croissance-devrait-rester-forte-pour-le-distributeur-darticles-de-sports-jd-sports-SUJFG6FEINHIJJ3JO5OQKS3FXQ\/",
        "source":"Lalibre.be",
        "published_at":1727454321000,
        "collected_at":1727696523630,
        "sentiment_label":"Neutral",
        "sentiment_probabolity":0.9999849796,
        "sentiment_vector":0.0
    }
]